{"config":{"output_file":null,"full_docs":false,"pub_only":false,"reachable_only":false,"distro_crate":false,"signatures":false,"borrow_data":false},"version":"0.19.0","compilation":{"directory":"/mnt/c/Users/rod_s/Desktop/Repos/AdventOfCode2020/day_01","program":"/home/sousa/.rustup/toolchains/stable-x86_64-unknown-linux-gnu/bin/rls","arguments":[],"output":"/mnt/c/Users/rod_s/Desktop/Repos/AdventOfCode2020/day_01/target/rls/debug/deps/libday_01-189d3d41f80dabd0.rmeta"},"prelude":{"crate_id":{"name":"day_01","disambiguator":[553997280341780060,10515918655684567176]},"crate_root":"src","external_crates":[{"file_name":"/mnt/c/Users/rod_s/Desktop/Repos/AdventOfCode2020/day_01/src/main.rs","num":1,"id":{"name":"std","disambiguator":[9744254129402482468,12445345062611050884]}},{"file_name":"/mnt/c/Users/rod_s/Desktop/Repos/AdventOfCode2020/day_01/src/main.rs","num":2,"id":{"name":"core","disambiguator":[9942249472390543209,15863006584859964888]}},{"file_name":"/mnt/c/Users/rod_s/Desktop/Repos/AdventOfCode2020/day_01/src/main.rs","num":3,"id":{"name":"compiler_builtins","disambiguator":[1795893391416169141,8075121191677772249]}},{"file_name":"/mnt/c/Users/rod_s/Desktop/Repos/AdventOfCode2020/day_01/src/main.rs","num":4,"id":{"name":"rustc_std_workspace_core","disambiguator":[1572415099058457553,2135166978196155506]}},{"file_name":"/mnt/c/Users/rod_s/Desktop/Repos/AdventOfCode2020/day_01/src/main.rs","num":5,"id":{"name":"alloc","disambiguator":[13603829026942055011,2471063435589406066]}},{"file_name":"/mnt/c/Users/rod_s/Desktop/Repos/AdventOfCode2020/day_01/src/main.rs","num":6,"id":{"name":"libc","disambiguator":[3150535728137067081,14418570958612661587]}},{"file_name":"/mnt/c/Users/rod_s/Desktop/Repos/AdventOfCode2020/day_01/src/main.rs","num":7,"id":{"name":"unwind","disambiguator":[7556171729466642164,9608667095244489899]}},{"file_name":"/mnt/c/Users/rod_s/Desktop/Repos/AdventOfCode2020/day_01/src/main.rs","num":8,"id":{"name":"cfg_if","disambiguator":[10806810126330215714,2553684360462883780]}},{"file_name":"/mnt/c/Users/rod_s/Desktop/Repos/AdventOfCode2020/day_01/src/main.rs","num":9,"id":{"name":"hashbrown","disambiguator":[1818097271180387350,15438349324121503308]}},{"file_name":"/mnt/c/Users/rod_s/Desktop/Repos/AdventOfCode2020/day_01/src/main.rs","num":10,"id":{"name":"rustc_std_workspace_alloc","disambiguator":[4437646126609693087,6536018436310544926]}},{"file_name":"/mnt/c/Users/rod_s/Desktop/Repos/AdventOfCode2020/day_01/src/main.rs","num":11,"id":{"name":"rustc_demangle","disambiguator":[11991037487279530558,3795792059683432706]}},{"file_name":"/mnt/c/Users/rod_s/Desktop/Repos/AdventOfCode2020/day_01/src/main.rs","num":12,"id":{"name":"addr2line","disambiguator":[1437858958743878161,787253638674005063]}},{"file_name":"/mnt/c/Users/rod_s/Desktop/Repos/AdventOfCode2020/day_01/src/main.rs","num":13,"id":{"name":"gimli","disambiguator":[4592710621585877372,1780610752140463821]}},{"file_name":"/mnt/c/Users/rod_s/Desktop/Repos/AdventOfCode2020/day_01/src/main.rs","num":14,"id":{"name":"object","disambiguator":[6338654217379816643,7168927451833124687]}},{"file_name":"/mnt/c/Users/rod_s/Desktop/Repos/AdventOfCode2020/day_01/src/main.rs","num":15,"id":{"name":"miniz_oxide","disambiguator":[18193432317814560663,14768114254071685082]}},{"file_name":"/mnt/c/Users/rod_s/Desktop/Repos/AdventOfCode2020/day_01/src/main.rs","num":16,"id":{"name":"adler","disambiguator":[12647259490832872807,4960225096531867135]}},{"file_name":"/mnt/c/Users/rod_s/Desktop/Repos/AdventOfCode2020/day_01/src/main.rs","num":17,"id":{"name":"panic_unwind","disambiguator":[8559662747993890479,3650412061717966503]}}],"span":{"file_name":"src/main.rs","byte_start":0,"byte_end":999,"line_start":1,"line_end":34,"column_start":1,"column_end":2}},"imports":[{"kind":"Use","ref_id":{"krate":1,"index":2223},"span":{"file_name":"src/main.rs","byte_start":13,"byte_end":17,"line_start":1,"line_end":1,"column_start":14,"column_end":18},"alias_span":null,"name":"File","value":"","parent":{"krate":0,"index":0}},{"kind":"Use","ref_id":{"krate":1,"index":3151},"span":{"file_name":"src/main.rs","byte_start":33,"byte_end":40,"line_start":2,"line_end":2,"column_start":15,"column_end":22},"alias_span":null,"name":"BufRead","value":"","parent":{"krate":0,"index":0}},{"kind":"Use","ref_id":{"krate":1,"index":2445},"span":{"file_name":"src/main.rs","byte_start":42,"byte_end":51,"line_start":2,"line_end":2,"column_start":24,"column_end":33},"alias_span":null,"name":"BufReader","value":"","parent":{"krate":0,"index":0}},{"kind":"Use","ref_id":{"krate":1,"index":2659},"span":{"file_name":"src/main.rs","byte_start":53,"byte_end":58,"line_start":2,"line_end":2,"column_start":35,"column_end":40},"alias_span":null,"name":"Error","value":"","parent":{"krate":0,"index":0}},{"kind":"Use","ref_id":{"krate":1,"index":7047},"span":{"file_name":"src/main.rs","byte_start":60,"byte_end":69,"line_start":2,"line_end":2,"column_start":42,"column_end":51},"alias_span":null,"name":"ErrorKind","value":"","parent":{"krate":0,"index":0}}],"defs":[{"kind":"Mod","id":{"krate":0,"index":0},"span":{"file_name":"src/main.rs","byte_start":0,"byte_end":999,"line_start":1,"line_end":34,"column_start":1,"column_end":2},"name":"","qualname":"::","value":"src/main.rs","parent":null,"children":[{"krate":0,"index":1},{"krate":0,"index":2},{"krate":0,"index":3},{"krate":0,"index":4},{"krate":0,"index":5},{"krate":0,"index":6},{"krate":0,"index":7},{"krate":0,"index":8},{"krate":0,"index":9}],"decl_id":null,"docs":"","sig":null,"attributes":[]},{"kind":"Function","id":{"krate":0,"index":9},"span":{"file_name":"src/main.rs","byte_start":76,"byte_end":80,"line_start":4,"line_end":4,"column_start":4,"column_end":8},"name":"main","qualname":"::main","value":"fn main()","parent":null,"children":[],"decl_id":null,"docs":"","sig":null,"attributes":[]},{"kind":"Local","id":{"krate":0,"index":2147483657},"span":{"file_name":"src/main.rs","byte_start":93,"byte_end":101,"line_start":5,"line_end":5,"column_start":9,"column_end":17},"name":"filename","qualname":"filename$HirId { owner: DefId(0:9 ~ day_01[7b03]::main), local_id: 1 }","value":"&str","parent":null,"children":[],"decl_id":null,"docs":"","sig":null,"attributes":[]},{"kind":"Local","id":{"krate":0,"index":1073741833},"span":{"file_name":"src/main.rs","byte_start":129,"byte_end":137,"line_start":6,"line_end":6,"column_start":9,"column_end":17},"name":"constant","qualname":"constant$HirId { owner: DefId(0:9 ~ day_01[7b03]::main), local_id: 2 }","value":"u32","parent":null,"children":[],"decl_id":null,"docs":"","sig":null,"attributes":[]},{"kind":"Local","id":{"krate":0,"index":3221225481},"span":{"file_name":"src/main.rs","byte_start":155,"byte_end":159,"line_start":8,"line_end":8,"column_start":9,"column_end":13},"name":"file","qualname":"file$HirId { owner: DefId(0:9 ~ day_01[7b03]::main), local_id: 3 }","value":"std::fs::File","parent":null,"children":[],"decl_id":null,"docs":"","sig":null,"attributes":[]},{"kind":"Local","id":{"krate":0,"index":536870921},"span":{"file_name":"src/main.rs","byte_start":201,"byte_end":207,"line_start":9,"line_end":9,"column_start":9,"column_end":15},"name":"reader","qualname":"reader$HirId { owner: DefId(0:9 ~ day_01[7b03]::main), local_id: 4 }","value":"std::io::BufReader<std::fs::File>","parent":null,"children":[],"decl_id":null,"docs":"","sig":null,"attributes":[]},{"kind":"Local","id":{"krate":0,"index":2684354569},"span":{"file_name":"src/main.rs","byte_start":241,"byte_end":245,"line_start":11,"line_end":11,"column_start":9,"column_end":13},"name":"data","qualname":"data$HirId { owner: DefId(0:9 ~ day_01[7b03]::main), local_id: 5 }","value":"std::vec::Vec<u32>","parent":null,"children":[],"decl_id":null,"docs":"","sig":null,"attributes":[]},{"kind":"Local","id":{"krate":0,"index":1610612745},"span":{"file_name":"src/main.rs","byte_start":287,"byte_end":291,"line_start":12,"line_end":12,"column_start":15,"column_end":19},"name":"line","qualname":"$HirId { owner: DefId(0:9 ~ day_01[7b03]::main), local_id: 88 }::line","value":"std::result::Result<std::string::String, std::io::Error>","parent":null,"children":[],"decl_id":null,"docs":"","sig":null,"attributes":[]},{"kind":"Local","id":{"krate":0,"index":3758096393},"span":{"file_name":"src/main.rs","byte_start":308,"byte_end":309,"line_start":12,"line_end":12,"column_start":36,"column_end":37},"name":"v","qualname":"$HirId { owner: DefId(0:9 ~ day_01[7b03]::main), local_id: 86 }::v","value":"std::string::String","parent":null,"children":[],"decl_id":null,"docs":"","sig":null,"attributes":[]},{"kind":"Local","id":{"krate":0,"index":268435465},"span":{"file_name":"src/main.rs","byte_start":330,"byte_end":331,"line_start":12,"line_end":12,"column_start":58,"column_end":59},"name":"e","qualname":"$HirId { owner: DefId(0:9 ~ day_01[7b03]::main), local_id: 84 }::e","value":"std::num::ParseIntError","parent":null,"children":[],"decl_id":null,"docs":"","sig":null,"attributes":[]},{"kind":"Local","id":{"krate":0,"index":234881033},"span":{"file_name":"src/main.rs","byte_start":446,"byte_end":469,"line_start":15,"line_end":15,"column_start":27,"column_end":50},"name":"iter","qualname":"iter$HirId { owner: DefId(0:9 ~ day_01[7b03]::main), local_id: 112 }","value":"std::iter::Enumerate<std::slice::Iter<u32>>","parent":null,"children":[],"decl_id":null,"docs":"","sig":null,"attributes":[]},{"kind":"Local","id":{"krate":0,"index":637534217},"span":{"file_name":"src/main.rs","byte_start":446,"byte_end":469,"line_start":15,"line_end":15,"column_start":27,"column_end":50},"name":"__next","qualname":"__next$HirId { owner: DefId(0:9 ~ day_01[7b03]::main), local_id: 100 }","value":"(usize, &u32)","parent":null,"children":[],"decl_id":null,"docs":"","sig":null,"attributes":[]},{"kind":"Local","id":{"krate":0,"index":2785017865},"span":{"file_name":"src/main.rs","byte_start":428,"byte_end":442,"line_start":15,"line_end":15,"column_start":9,"column_end":23},"name":"val","qualname":"val$HirId { owner: DefId(0:9 ~ day_01[7b03]::main), local_id: 101 }","value":"(usize, &u32)","parent":null,"children":[],"decl_id":null,"docs":"","sig":null,"attributes":[]},{"kind":"Local","id":{"krate":0,"index":1342177289},"span":{"file_name":"src/main.rs","byte_start":429,"byte_end":434,"line_start":15,"line_end":15,"column_start":10,"column_end":15},"name":"index","qualname":"index$HirId { owner: DefId(0:9 ~ day_01[7b03]::main), local_id: 10 }","value":"usize","parent":null,"children":[],"decl_id":null,"docs":"","sig":null,"attributes":[]},{"kind":"Local","id":{"krate":0,"index":3489660937},"span":{"file_name":"src/main.rs","byte_start":436,"byte_end":441,"line_start":15,"line_end":15,"column_start":17,"column_end":22},"name":"value","qualname":"value$HirId { owner: DefId(0:9 ~ day_01[7b03]::main), local_id: 11 }","value":"&u32","parent":null,"children":[],"decl_id":null,"docs":"","sig":null,"attributes":[]},{"kind":"Local","id":{"krate":0,"index":1895825417},"span":{"file_name":"src/main.rs","byte_start":522,"byte_end":545,"line_start":17,"line_end":17,"column_start":42,"column_end":65},"name":"iter","qualname":"iter$HirId { owner: DefId(0:9 ~ day_01[7b03]::main), local_id: 142 }","value":"std::iter::Enumerate<std::slice::Iter<u32>>","parent":null,"children":[],"decl_id":null,"docs":"","sig":null,"attributes":[]},{"kind":"Local","id":{"krate":0,"index":1090519049},"span":{"file_name":"src/main.rs","byte_start":522,"byte_end":545,"line_start":17,"line_end":17,"column_start":42,"column_end":65},"name":"__next","qualname":"__next$HirId { owner: DefId(0:9 ~ day_01[7b03]::main), local_id: 130 }","value":"(usize, &u32)","parent":null,"children":[],"decl_id":null,"docs":"","sig":null,"attributes":[]},{"kind":"Local","id":{"krate":0,"index":3238002697},"span":{"file_name":"src/main.rs","byte_start":493,"byte_end":518,"line_start":17,"line_end":17,"column_start":13,"column_end":38},"name":"val","qualname":"val$HirId { owner: DefId(0:9 ~ day_01[7b03]::main), local_id: 131 }","value":"(usize, &u32)","parent":null,"children":[],"decl_id":null,"docs":"","sig":null,"attributes":[]},{"kind":"Local","id":{"krate":0,"index":2952790025},"span":{"file_name":"src/main.rs","byte_start":494,"byte_end":503,"line_start":17,"line_end":17,"column_start":14,"column_end":23},"name":"sub_index","qualname":"sub_index$HirId { owner: DefId(0:9 ~ day_01[7b03]::main), local_id: 13 }","value":"usize","parent":null,"children":[],"decl_id":null,"docs":"","sig":null,"attributes":[]},{"kind":"Local","id":{"krate":0,"index":1879048201},"span":{"file_name":"src/main.rs","byte_start":505,"byte_end":517,"line_start":17,"line_end":17,"column_start":25,"column_end":37},"name":"second_value","qualname":"second_value$HirId { owner: DefId(0:9 ~ day_01[7b03]::main), local_id: 14 }","value":"&u32","parent":null,"children":[],"decl_id":null,"docs":"","sig":null,"attributes":[]}],"impls":[],"refs":[{"kind":"Mod","span":{"file_name":"src/main.rs","byte_start":4,"byte_end":7,"line_start":1,"line_end":1,"column_start":5,"column_end":8},"ref_id":{"krate":1,"index":0}},{"kind":"Mod","span":{"file_name":"src/main.rs","byte_start":9,"byte_end":11,"line_start":1,"line_end":1,"column_start":10,"column_end":12},"ref_id":{"krate":1,"index":2201}},{"kind":"Type","span":{"file_name":"src/main.rs","byte_start":23,"byte_end":26,"line_start":2,"line_end":2,"column_start":5,"column_end":8},"ref_id":{"krate":1,"index":3151}},{"kind":"Type","span":{"file_name":"src/main.rs","byte_start":28,"byte_end":30,"line_start":2,"line_end":2,"column_start":10,"column_end":12},"ref_id":{"krate":1,"index":3151}},{"kind":"Type","span":{"file_name":"src/main.rs","byte_start":23,"byte_end":26,"line_start":2,"line_end":2,"column_start":5,"column_end":8},"ref_id":{"krate":1,"index":2445}},{"kind":"Type","span":{"file_name":"src/main.rs","byte_start":28,"byte_end":30,"line_start":2,"line_end":2,"column_start":10,"column_end":12},"ref_id":{"krate":1,"index":2445}},{"kind":"Type","span":{"file_name":"src/main.rs","byte_start":23,"byte_end":26,"line_start":2,"line_end":2,"column_start":5,"column_end":8},"ref_id":{"krate":1,"index":2659}},{"kind":"Type","span":{"file_name":"src/main.rs","byte_start":28,"byte_end":30,"line_start":2,"line_end":2,"column_start":10,"column_end":12},"ref_id":{"krate":1,"index":2659}},{"kind":"Type","span":{"file_name":"src/main.rs","byte_start":23,"byte_end":26,"line_start":2,"line_end":2,"column_start":5,"column_end":8},"ref_id":{"krate":1,"index":7047}},{"kind":"Type","span":{"file_name":"src/main.rs","byte_start":28,"byte_end":30,"line_start":2,"line_end":2,"column_start":10,"column_end":12},"ref_id":{"krate":1,"index":7047}},{"kind":"Function","span":{"file_name":"src/main.rs","byte_start":183,"byte_end":189,"line_start":8,"line_end":8,"column_start":37,"column_end":43},"ref_id":{"krate":2,"index":6071}},{"kind":"Function","span":{"file_name":"src/main.rs","byte_start":168,"byte_end":172,"line_start":8,"line_end":8,"column_start":22,"column_end":26},"ref_id":{"krate":1,"index":2241}},{"kind":"Type","span":{"file_name":"src/main.rs","byte_start":162,"byte_end":166,"line_start":8,"line_end":8,"column_start":16,"column_end":20},"ref_id":{"krate":1,"index":2223}},{"kind":"Variable","span":{"file_name":"src/main.rs","byte_start":173,"byte_end":181,"line_start":8,"line_end":8,"column_start":27,"column_end":35},"ref_id":{"krate":0,"index":2147483657}},{"kind":"Function","span":{"file_name":"src/main.rs","byte_start":221,"byte_end":224,"line_start":9,"line_end":9,"column_start":29,"column_end":32},"ref_id":{"krate":1,"index":2453}},{"kind":"Type","span":{"file_name":"src/main.rs","byte_start":210,"byte_end":219,"line_start":9,"line_end":9,"column_start":18,"column_end":27},"ref_id":{"krate":1,"index":2445}},{"kind":"Variable","span":{"file_name":"src/main.rs","byte_start":225,"byte_end":229,"line_start":9,"line_end":9,"column_start":33,"column_end":37},"ref_id":{"krate":0,"index":3221225481}},{"kind":"Type","span":{"file_name":"src/main.rs","byte_start":247,"byte_end":250,"line_start":11,"line_end":11,"column_start":15,"column_end":18},"ref_id":{"krate":5,"index":4551}},{"kind":"Function","span":{"file_name":"src/main.rs","byte_start":409,"byte_end":415,"line_start":13,"line_end":13,"column_start":36,"column_end":42},"ref_id":{"krate":2,"index":6071}},{"kind":"Function","span":{"file_name":"src/main.rs","byte_start":383,"byte_end":390,"line_start":13,"line_end":13,"column_start":10,"column_end":17},"ref_id":{"krate":2,"index":5336}},{"kind":"Type","span":{"file_name":"src/main.rs","byte_start":393,"byte_end":399,"line_start":13,"line_end":13,"column_start":20,"column_end":26},"ref_id":{"krate":2,"index":31890}},{"kind":"Function","span":{"file_name":"src/main.rs","byte_start":282,"byte_end":285,"line_start":12,"line_end":12,"column_start":10,"column_end":13},"ref_id":{"krate":2,"index":5298}},{"kind":"Function","span":{"file_name":"src/main.rs","byte_start":265,"byte_end":270,"line_start":11,"line_end":11,"column_start":33,"column_end":38},"ref_id":{"krate":1,"index":3158}},{"kind":"Variable","span":{"file_name":"src/main.rs","byte_start":258,"byte_end":264,"line_start":11,"line_end":11,"column_start":26,"column_end":32},"ref_id":{"krate":0,"index":536870921}},{"kind":"Function","span":{"file_name":"src/main.rs","byte_start":298,"byte_end":306,"line_start":12,"line_end":12,"column_start":26,"column_end":34},"ref_id":{"krate":2,"index":6036}},{"kind":"Variable","span":{"file_name":"src/main.rs","byte_start":293,"byte_end":297,"line_start":12,"line_end":12,"column_start":21,"column_end":25},"ref_id":{"krate":0,"index":1610612745}},{"kind":"Function","span":{"file_name":"src/main.rs","byte_start":321,"byte_end":328,"line_start":12,"line_end":12,"column_start":49,"column_end":56},"ref_id":{"krate":2,"index":6029}},{"kind":"Function","span":{"file_name":"src/main.rs","byte_start":313,"byte_end":318,"line_start":12,"line_end":12,"column_start":41,"column_end":46},"ref_id":{"krate":2,"index":8886}},{"kind":"Variable","span":{"file_name":"src/main.rs","byte_start":311,"byte_end":312,"line_start":12,"line_end":12,"column_start":39,"column_end":40},"ref_id":{"krate":0,"index":3758096393}},{"kind":"Function","span":{"file_name":"src/main.rs","byte_start":340,"byte_end":343,"line_start":12,"line_end":12,"column_start":68,"column_end":71},"ref_id":{"krate":1,"index":2678}},{"kind":"Type","span":{"file_name":"src/main.rs","byte_start":333,"byte_end":338,"line_start":12,"line_end":12,"column_start":61,"column_end":66},"ref_id":{"krate":1,"index":2659}},{"kind":"Type","span":{"file_name":"src/main.rs","byte_start":355,"byte_end":366,"line_start":12,"line_end":12,"column_start":83,"column_end":94},"ref_id":{"krate":1,"index":7072}},{"kind":"Type","span":{"file_name":"src/main.rs","byte_start":344,"byte_end":353,"line_start":12,"line_end":12,"column_start":72,"column_end":81},"ref_id":{"krate":1,"index":7047}},{"kind":"Variable","span":{"file_name":"src/main.rs","byte_start":368,"byte_end":369,"line_start":12,"line_end":12,"column_start":96,"column_end":97},"ref_id":{"krate":0,"index":268435465}},{"kind":"Function","span":{"file_name":"src/main.rs","byte_start":451,"byte_end":455,"line_start":15,"line_end":15,"column_start":32,"column_end":36},"ref_id":{"krate":2,"index":8038}},{"kind":"Variable","span":{"file_name":"src/main.rs","byte_start":446,"byte_end":450,"line_start":15,"line_end":15,"column_start":27,"column_end":31},"ref_id":{"krate":0,"index":2684354569}},{"kind":"Variable","span":{"file_name":"src/main.rs","byte_start":428,"byte_end":442,"line_start":15,"line_end":15,"column_start":9,"column_end":23},"ref_id":{"krate":2,"index":31737}},{"kind":"Function","span":{"file_name":"src/main.rs","byte_start":527,"byte_end":531,"line_start":17,"line_end":17,"column_start":47,"column_end":51},"ref_id":{"krate":2,"index":8038}},{"kind":"Variable","span":{"file_name":"src/main.rs","byte_start":522,"byte_end":526,"line_start":17,"line_end":17,"column_start":42,"column_end":46},"ref_id":{"krate":0,"index":2684354569}},{"kind":"Variable","span":{"file_name":"src/main.rs","byte_start":493,"byte_end":518,"line_start":17,"line_end":17,"column_start":13,"column_end":38},"ref_id":{"krate":2,"index":31737}},{"kind":"Variable","span":{"file_name":"src/main.rs","byte_start":563,"byte_end":572,"line_start":18,"line_end":18,"column_start":16,"column_end":25},"ref_id":{"krate":0,"index":2952790025}},{"kind":"Variable","span":{"file_name":"src/main.rs","byte_start":576,"byte_end":581,"line_start":18,"line_end":18,"column_start":29,"column_end":34},"ref_id":{"krate":0,"index":1342177289}},{"kind":"Variable","span":{"file_name":"src/main.rs","byte_start":807,"byte_end":812,"line_start":26,"line_end":26,"column_start":16,"column_end":21},"ref_id":{"krate":0,"index":3489660937}},{"kind":"Variable","span":{"file_name":"src/main.rs","byte_start":815,"byte_end":827,"line_start":26,"line_end":26,"column_start":24,"column_end":36},"ref_id":{"krate":0,"index":1879048201}},{"kind":"Variable","span":{"file_name":"src/main.rs","byte_start":831,"byte_end":839,"line_start":26,"line_end":26,"column_start":40,"column_end":48},"ref_id":{"krate":0,"index":1073741833}},{"kind":"Function","span":{"file_name":"/home/sousa/.rustup/toolchains/stable-x86_64-unknown-linux-gnu/lib/rustlib/src/rust/library/std/src/macros.rs","byte_start":24619,"byte_end":24652,"line_start":96,"line_end":96,"column_start":28,"column_end":61},"ref_id":{"krate":2,"index":6544}},{"kind":"Variable","span":{"file_name":"src/main.rs","byte_start":883,"byte_end":888,"line_start":27,"line_end":27,"column_start":42,"column_end":47},"ref_id":{"krate":0,"index":3489660937}},{"kind":"Variable","span":{"file_name":"src/main.rs","byte_start":890,"byte_end":902,"line_start":27,"line_end":27,"column_start":49,"column_end":61},"ref_id":{"krate":0,"index":1879048201}},{"kind":"Variable","span":{"file_name":"src/main.rs","byte_start":904,"byte_end":909,"line_start":27,"line_end":27,"column_start":63,"column_end":68},"ref_id":{"krate":0,"index":3489660937}},{"kind":"Variable","span":{"file_name":"src/main.rs","byte_start":912,"byte_end":924,"line_start":27,"line_end":27,"column_start":71,"column_end":83},"ref_id":{"krate":0,"index":1879048201}},{"kind":"Function","span":{"file_name":"/home/sousa/.rustup/toolchains/stable-x86_64-unknown-linux-gnu/lib/rustlib/src/rust/library/std/src/macros.rs","byte_start":24619,"byte_end":24652,"line_start":96,"line_end":96,"column_start":28,"column_end":61},"ref_id":{"krate":2,"index":6537}},{"kind":"Function","span":{"file_name":"/home/sousa/.rustup/toolchains/stable-x86_64-unknown-linux-gnu/lib/rustlib/src/rust/library/std/src/macros.rs","byte_start":24619,"byte_end":24652,"line_start":96,"line_end":96,"column_start":28,"column_end":61},"ref_id":{"krate":2,"index":6537}},{"kind":"Function","span":{"file_name":"/home/sousa/.rustup/toolchains/stable-x86_64-unknown-linux-gnu/lib/rustlib/src/rust/library/std/src/macros.rs","byte_start":24619,"byte_end":24652,"line_start":96,"line_end":96,"column_start":28,"column_end":61},"ref_id":{"krate":2,"index":6537}},{"kind":"Function","span":{"file_name":"src/main.rs","byte_start":957,"byte_end":961,"line_start":28,"line_end":28,"column_start":31,"column_end":35},"ref_id":{"krate":1,"index":4488}},{"kind":"Mod","span":{"file_name":"src/main.rs","byte_start":943,"byte_end":946,"line_start":28,"line_end":28,"column_start":17,"column_end":20},"ref_id":{"krate":1,"index":0}},{"kind":"Mod","span":{"file_name":"src/main.rs","byte_start":948,"byte_end":955,"line_start":28,"line_end":28,"column_start":22,"column_end":29},"ref_id":{"krate":1,"index":4312}}],"macro_refs":[],"relations":[]}